AUTHORS
ChangeLog
MANIFEST.in
README.rst
requirements.txt
setup.cfg
setup.py
leonardo_gallery/__init__.py
leonardo_gallery/views.py
leonardo_gallery.egg-info/PKG-INFO
leonardo_gallery.egg-info/SOURCES.txt
leonardo_gallery.egg-info/dependency_links.txt
leonardo_gallery.egg-info/not-zip-safe
leonardo_gallery.egg-info/pbr.json
leonardo_gallery.egg-info/top_level.txt
leonardo_gallery/apps/__init__.py
leonardo_gallery/apps/gallery.py
leonardo_gallery/static/css/default-skin.css
leonardo_gallery/static/css/default-skin.png
leonardo_gallery/static/css/default-skin.svg
leonardo_gallery/static/css/photoswipe.css
leonardo_gallery/static/css/preloader.gif
leonardo_gallery/static/js/photoswipe-ui-default.js
leonardo_gallery/static/js/photoswipe-ui-default.min.js
leonardo_gallery/static/js/photoswipe.js
leonardo_gallery/static/js/photoswipe.min.js
leonardo_gallery/static/js/angular/angular-carousel.min.js
leonardo_gallery/static/js/angular/angular-touch.min.js
leonardo_gallery/templates/media/directory_detail.html
leonardo_gallery/templates/widget/mediagallery/photoswipe.html